pyapplemusicapi/__init__.py
pyapplemusicapi/base.py
pyapplemusicapi/exceptions.py
pyapplemusicapi/search.py
pyapplemusicapi-2.0.0.dist-info/METADATA
pyapplemusicapi-2.0.0.dist-info/WHEEL
pyapplemusicapi-2.0.0.dist-info/top_level.txt
pyapplemusicapi-2.0.0.dist-info/RECORD
