Metadata-Version: 2.1
Name: pyapplemusicapi
Version: 2.0.0
Summary: A simple Python interface to search the Apple Music and Apple TV libraries
Home-page: https://github.com/queengooborg/pyapplemusicapi
Author: Vinyl Da.i'gyu-Kazotetsu
Author-email: queen@gooborg.com
Maintainer: Vinyl Da.i'gyu-Kazotetsu
Maintainer-email: queen@gooborg.com
License: http://www.gnu.org/licenses/gpl-3.0.html
Project-URL: Bug Tracker, https://github.com/queengooborg/pyapplemusicapi/issues
Platform: any
Classifier: Development Status :: 5 - Production/Stable
Classifier: Programming Language :: Python :: 3
Classifier: License :: OSI Approved :: GNU General Public License v3 (GPLv3)
Classifier: Natural Language :: English
Classifier: Operating System :: OS Independent
Requires-Python: >=3.6
Requires-Dist: CacheControl (>=0.11.6)
Requires-Dist: requests (>=2.20.0)
